pdscheduling/__init__.py
pdscheduling-0.2.2.dist-info/LICENSE
pdscheduling-0.2.2.dist-info/WHEEL
pdscheduling-0.2.2.dist-info/METADATA
pdscheduling-0.2.2.dist-info/RECORD
