Metadata-Version: 2.1
Name: pdscheduling
Version: 0.2.2
Summary: 
License: MIT
Author: Roman
Author-email: roman@optduty.com
Requires-Python: >=3.8,<4.0
Classifier: License :: OSI Approved :: MIT License
Classifier: Programming Language :: Python :: 3
Classifier: Programming Language :: Python :: 3.8
Classifier: Programming Language :: Python :: 3.9
Requires-Dist: pdpyras (>=4.3.0,<5.0.0)
Requires-Dist: requests (>=2.25.1,<3.0.0)
